{"cameraMode":{"drawMode":0,"name":"Shaded","section":"Shading Mode"},"sceneLighting":true,"audioPlay":false,"sceneViewState":{"m_AlwaysRefresh":false,"showFog":true,"showSkybox":true,"showFlares":true,"showImageEffects":true,"showParticleSystems":true,"showVisualEffectGraphs":true,"m_FxEnabled":true},"in2DMode":false,"pivot":{"x":1.0799999237060547,"y":1.239999771118164,"z":-2.0399999618530275},"rotation":{"x":-0.1300659328699112,"y":0.8151989579200745,"z":-0.20105716586112977,"w":-0.5273588299751282},"size":12.12435531616211,"orthographic":false}